alibabacloud_cms20240330/__init__.py
alibabacloud_cms20240330/client.py
alibabacloud_cms20240330/models/__init__.py
alibabacloud_cms20240330/models/_addon_meta.py
alibabacloud_cms20240330/models/_alert_event_integration_policy_for_modify.py
alibabacloud_cms20240330/models/_alert_event_integration_policy_for_view.py
alibabacloud_cms20240330/models/_alert_rule_action.py
alibabacloud_cms20240330/models/_alert_rule_alert_metric_filter_def.py
alibabacloud_cms20240330/models/_alert_rule_alert_metric_input.py
alibabacloud_cms20240330/models/_alert_rule_alert_metric_input_filter_value.py
alibabacloud_cms20240330/models/_alert_rule_alert_metric_input_param_value.py
alibabacloud_cms20240330/models/_alert_rule_alert_metric_param_def.py
alibabacloud_cms20240330/models/_alert_rule_condition.py
alibabacloud_cms20240330/models/_alert_rule_data_source.py
alibabacloud_cms20240330/models/_alert_rule_label_filter.py
alibabacloud_cms20240330/models/_alert_rule_notification.py
alibabacloud_cms20240330/models/_alert_rule_notification_filter.py
alibabacloud_cms20240330/models/_alert_rule_query.py
alibabacloud_cms20240330/models/_alert_rule_send.py
alibabacloud_cms20240330/models/_alert_rule_sls_query_join.py
alibabacloud_cms20240330/models/_alert_rule_time_span.py
alibabacloud_cms20240330/models/_biz_trace_config.py
alibabacloud_cms20240330/models/_change_resource_group_request.py
alibabacloud_cms20240330/models/_change_resource_group_response.py
alibabacloud_cms20240330/models/_change_resource_group_response_body.py
alibabacloud_cms20240330/models/_cms_event_for_view.py
alibabacloud_cms20240330/models/_contact_for_incident_view.py
alibabacloud_cms20240330/models/_create_addon_release_request.py
alibabacloud_cms20240330/models/_create_addon_release_response.py
alibabacloud_cms20240330/models/_create_addon_release_response_body.py
alibabacloud_cms20240330/models/_create_agg_task_group_request.py
alibabacloud_cms20240330/models/_create_agg_task_group_response.py
alibabacloud_cms20240330-4.2.0.dist-info/LICENSE
alibabacloud_cms20240330-4.2.0.dist-info/METADATA
alibabacloud_cms20240330-4.2.0.dist-info/WHEEL
alibabacloud_cms20240330-4.2.0.dist-info/top_level.txt
alibabacloud_cms20240330-4.2.0.dist-info/RECORD
